{
  "localizacion": "23.13498, -82.38796",
  "servicio_a_domicilio": {
    "valor": false
  },
  "productos": [
    {
      "id": 1,
      "nombre": "Toallitas húmedas",
      "precio": 800,
      "unidad de medida":"60",
      "categoria": "Higiene",
      "marca": "Cotidian",
      "disponible": true,
      "descuento": 0.0
    },
    {
      "id": 2,
      "nombre": "Pañales",
      "precio": 4400,
      "unidad de medida":"8u",
      "categoria": "Higiene",
      "marca": "Prevail",
      "disponible": true,
      "descuento": 0.0
    },
    {
      "id": 3,
      "nombre": "Pan",
      "precio": 0.00,
      "unidad de medida":"",
      "categoria": "alimentos",
      "marca": "",
      "disponible": false,
      "descuento": 0.0
    },
    {
      "id": 4,
      "nombre": "Leche",
      "precio": 2500,
      "unidad de medida":"1lt",
      "categoria": "alimentos",
      "marca": "Macro fut",
      "disponible": true,
      "descuento": 0.0
    },
    {
      "id": 5,
      "nombre": "yogurt",
      "precio": 0.00,
      "unidad de medida":"",
      "categoria": "alimentos",
      "marca": "",
      "disponible": false,
      "descuento": 0.0
    },
    {
      "id": 6,
      "nombre": "pollo",
      "precio": 7500,
      "unidad de medida":"10kg",
      "categoria": "alimentos",
      "marca": "Tyson",
      "disponible": true,
      "descuento": 0.0
    },
    {
      "id": 7,
      "nombre": "picadillo",
      "precio": 800,
      "unidad de medida":"500gr",
      "categoria": "alimentos",
      "marca": "Bravo",
      "disponible": true,
      "descuento": 0.0
    },
    {
      "id": 8,
      "nombre": "huevo",
      "precio": 0.00,
      "unidad de medida":"",
      "categoria": "alimentos",
      "marca": "",
      "disponible": false,
      "descuento": 0.0
    },
    {
      "id": 9,
      "nombre": "queso",
      "precio": 2300,
      "unidad de medida":"1lb",
      "categoria": "alimentos",
      "marca": "Gouda",
      "disponible": true,
      "descuento": 0.0
    },
    {
      "id": 10,
      "nombre": "sopas",
      "precio": 160,
      "unidad de medida":"50gr",
      "categoria": "alimentos",
      "marca": "Kaldin",
      "disponible": true,
      "descuento": 0.0
    },
    {
      "id": 11,
      "nombre": "arroz",
      "precio": 580,
      "unidad de medida":"1kg",
      "categoria": "alimentos",
      "marca": "Vivo",
      "disponible": true,
      "descuento": 0.0
    },
    {
      "id": 12,
      "nombre": "frijoles",
      "precio": 0.00,
      "unidad de medida":"",
      "categoria": "alimentos",
      "marca": "",
      "disponible": false,
      "descuento": 0.0
    },
    {
      "id": 13,
      "nombre": "aceite",
      "precio": 890,
      "unidad de medida":"1l",
      "categoria": "alimentos",
      "marca": "Saude",
      "disponible": true,
      "descuento": 0.0
    },{
      "id": 14,
      "nombre": "cereales",
      "precio":550,
      "unidad de medida":"346gr",
      "categoria": "alimentos",
      "marca": "Kiggins",
      "disponible":true,
      "descuento": 0.0
    },
    {
      "id": 15,
      "nombre": "galletas",
      "precio": 150,
      "unidad de medida":"200gr",
      "categoria": "alimentos",
      "marca": "Festival",
      "disponible": true,
      "descuento": 0.0
    }
    ]
}